[
  {
    "text": "find another recipe",
    "intent": "next_page",
    "intent_prediction": {
      "name": "choose_recipe",
      "confidence": 0.4808506667613983
    }
  },
  {
    "text": "I don't like them",
    "intent": "next_page",
    "intent_prediction": {
      "name": "deny",
      "confidence": 0.20842085778713226
    }
  },
  {
    "text": "Find another one",
    "intent": "next_page",
    "intent_prediction": {
      "name": "choose_recipe",
      "confidence": 0.6094903945922852
    }
  },
  {
    "text": "OK, I'm ready to start",
    "intent": "start_cooking",
    "intent_prediction": {
      "name": "next_step",
      "confidence": 0.7961375713348389
    }
  },
  {
    "text": "Go on",
    "intent": "next_step",
    "intent_prediction": {
      "name": "affirm",
      "confidence": 0.20512032508850098
    }
  },
  {
    "text": "amazing",
    "intent": "affirm",
    "intent_prediction": {
      "name": "search_recipe",
      "confidence": 0.2261059433221817
    }
  },
  {
    "text": "perfect",
    "intent": "affirm",
    "intent_prediction": {
      "name": "search_recipe",
      "confidence": 0.23436130583286285
    }
  },
  {
    "text": "amazing!",
    "intent": "affirm",
    "intent_prediction": {
      "name": "search_recipe",
      "confidence": 0.2261059433221817
    }
  }
]